mycalc/calculator.py
jonghocal-0.0.1.dist-info/METADATA
jonghocal-0.0.1.dist-info/WHEEL
jonghocal-0.0.1.dist-info/top_level.txt
jonghocal-0.0.1.dist-info/RECORD
