Metadata-Version: 2.1
Name: jonghocal
Version: 0.0.1
Summary: oss-dev my jonghocal 0001
Home-page: 
Download-URL: 
Author: jonghokim
Author-email: qkdhfh8@naver.com
License: UNKNOWN
Platform: UNKNOWN
Classifier: Programming Language :: Python :: 3
Classifier: Operating System :: OS Independent
